starred_repo_finder/__init__.py
starred_repo_finder/__version__.py
starred_repo_finder/cli.py
starred_repo_finder/starred_repo_finder.py
starred_repo_finder-1.7.0.dist-info/licenses/LICENSE
tests/__init__.py
tests/test_cli.py
tests/test_imports.py
tests/test_starred_repo_finder.py
tests/test_version.py
starred_repo_finder-1.7.0.dist-info/METADATA
starred_repo_finder-1.7.0.dist-info/WHEEL
starred_repo_finder-1.7.0.dist-info/entry_points.txt
starred_repo_finder-1.7.0.dist-info/top_level.txt
starred_repo_finder-1.7.0.dist-info/RECORD
