Metadata-Version: 2.4
Name: starred_repo_finder
Version: 1.7.0
Summary: A simple command line tool to find and explore GitHub repositories through stargazers for a given repository.
Home-page: https://github.com/tylercb/starred_repo_finder
Author: Tyler Hanway
Author-email: hanway.tyler@gmail.com
License: MIT
Classifier: Development Status :: 3 - Alpha
Classifier: Intended Audience :: Developers
Classifier: License :: OSI Approved :: MIT License
Classifier: Programming Language :: Python :: 3.8
License-File: LICENSE
Requires-Dist: click
Requires-Dist: requests
Requires-Dist: rich
Dynamic: author
Dynamic: author-email
Dynamic: classifier
Dynamic: description
Dynamic: description-content-type
Dynamic: home-page
Dynamic: license
Dynamic: license-file
Dynamic: requires-dist
Dynamic: summary
